ElasticPySearch/__init__.py
ElasticPySearch-1.0.0.dist-info/LICENSE
ElasticPySearch-1.0.0.dist-info/METADATA
ElasticPySearch-1.0.0.dist-info/WHEEL
ElasticPySearch-1.0.0.dist-info/top_level.txt
ElasticPySearch-1.0.0.dist-info/RECORD
