Metadata-Version: 2.1
Name: ElasticPySearch
Version: 1.0.0
Summary: Elastic Search Python Wrapper
Home-page: https://github.com/bhagatsajan0073/elastipysearch
Author: Sajan Kumar Bhagat
Author-email: bhagat.sajan0073@example.com
License: UNKNOWN
Platform: UNKNOWN
Classifier: Programming Language :: Python :: 3
Classifier: License :: OSI Approved :: MIT License
Classifier: Operating System :: OS Independent
Requires-Python: >=3.6
